dm_env/__init__.py
dm_env/_abstract_test_mixin.py
dm_env/_environment.py
dm_env/_environment_test.py
dm_env/_metadata.py
dm_env/auto_reset_environment.py
dm_env/auto_reset_environment_test.py
dm_env/specs.py
dm_env/specs_test.py
dm_env/test_utils.py
dm_env/test_utils_test.py
dm_env-1.5.dist-info/LICENSE
dm_env-1.5.dist-info/METADATA
dm_env-1.5.dist-info/WHEEL
dm_env-1.5.dist-info/top_level.txt
dm_env-1.5.dist-info/RECORD
