Metadata-Version: 1.1
Name: dm-env
Version: 1.5
Summary: A Python interface for Reinforcement Learning environments.
Home-page: UNKNOWN
Author: DeepMind
Author-email: UNKNOWN
License: Apache License, Version 2.0
Keywords: reinforcement-learning python machine learning
Platform: UNKNOWN
Classifier: Development Status :: 5 - Production/Stable
Classifier: Environment :: Console
Classifier: Intended Audience :: Science/Research
Classifier: License :: OSI Approved :: Apache Software License
Classifier: Operating System :: POSIX :: Linux
Classifier: Operating System :: Microsoft :: Windows
Classifier: Operating System :: MacOS :: MacOS X
Classifier: Programming Language :: Python :: 3.6
Classifier: Programming Language :: Python :: 3.7
Classifier: Topic :: Scientific/Engineering :: Artificial Intelligence
